pxtool/__init__.py
pxtool/json_deal.py
pxtool/set_log.py
pxtool-0.1.2.dist-info/METADATA
pxtool-0.1.2.dist-info/WHEEL
pxtool-0.1.2.dist-info/top_level.txt
pxtool-0.1.2.dist-info/RECORD
