Metadata-Version: 2.4
Name: pxtool
Version: 0.1.2
Summary: python工具集
Home-page: https://github.com/pxpy/pxtool
Author: px
Author-email: panxin@panxin.me
Classifier: Programming Language :: Python :: 3
Classifier: License :: OSI Approved :: MIT License
Classifier: Operating System :: OS Independent
Requires-Python: >=3.6
Requires-Dist: termcolor>=2.0.0
Dynamic: author
Dynamic: author-email
Dynamic: classifier
Dynamic: description
Dynamic: description-content-type
Dynamic: home-page
Dynamic: requires-dist
Dynamic: requires-python
Dynamic: summary
